aws_whoami.py
aws_whoami-1.2.0.dist-info/entry_points.txt
aws_whoami-1.2.0.dist-info/LICENSE
aws_whoami-1.2.0.dist-info/WHEEL
aws_whoami-1.2.0.dist-info/METADATA
aws_whoami-1.2.0.dist-info/RECORD
