Metadata-Version: 2.1
Name: aws-whoami
Version: 1.2.0
Summary: A tool and library for determining what AWS account and identity you're using
Home-page: https://github.com/benkehoe/aws-whoami
License: Apache-2.0
Author: Ben Kehoe
Author-email: ben@kehoe.io
Requires-Python: >=2.7, !=3.0.*, !=3.1.*, !=3.2.*
Classifier: Development Status :: 4 - Beta
Classifier: Intended Audience :: Developers
Classifier: Intended Audience :: System Administrators
Classifier: License :: OSI Approved :: Apache Software License
Classifier: Operating System :: OS Independent
Classifier: Programming Language :: Python :: 2
Classifier: Programming Language :: Python :: 2.7
Classifier: Programming Language :: Python :: 3
Classifier: Programming Language :: Python :: 3.4
Classifier: Programming Language :: Python :: 3.5
Classifier: Programming Language :: Python :: 3.6
Classifier: Programming Language :: Python :: 3.7
Classifier: Programming Language :: Python :: 3.8
Classifier: Topic :: Utilities
Requires-Dist: boto3
Project-URL: Repository, https://github.com/benkehoe/aws-whoami
